odoo8_addon_currency_rate_date_check-8.0.1.0.0.99.dev19-py3.8-nspkg.pth
odoo_addons/currency_rate_date_check/__init__.py
odoo_addons/currency_rate_date_check/__openerp__.py
odoo_addons/currency_rate_date_check/company.py
odoo_addons/currency_rate_date_check/company_view.xml
odoo_addons/currency_rate_date_check/currency_rate_date_check.py
odoo_addons/currency_rate_date_check/i18n/am.po
odoo_addons/currency_rate_date_check/i18n/ar.po
odoo_addons/currency_rate_date_check/i18n/ca.po
odoo_addons/currency_rate_date_check/i18n/currency_rate_date_check.pot
odoo_addons/currency_rate_date_check/i18n/da.po
odoo_addons/currency_rate_date_check/i18n/de.po
odoo_addons/currency_rate_date_check/i18n/el_GR.po
odoo_addons/currency_rate_date_check/i18n/es.po
odoo_addons/currency_rate_date_check/i18n/es_ES.po
odoo_addons/currency_rate_date_check/i18n/es_MX.po
odoo_addons/currency_rate_date_check/i18n/eu.po
odoo_addons/currency_rate_date_check/i18n/fi.po
odoo_addons/currency_rate_date_check/i18n/fr.po
odoo_addons/currency_rate_date_check/i18n/fr_CA.po
odoo_addons/currency_rate_date_check/i18n/fr_FR.po
odoo_addons/currency_rate_date_check/i18n/hr.po
odoo_addons/currency_rate_date_check/i18n/hr_HR.po
odoo_addons/currency_rate_date_check/i18n/it.po
odoo_addons/currency_rate_date_check/i18n/nb.po
odoo_addons/currency_rate_date_check/i18n/nb_NO.po
odoo_addons/currency_rate_date_check/i18n/nl.po
odoo_addons/currency_rate_date_check/i18n/nl_BE.po
odoo_addons/currency_rate_date_check/i18n/nl_NL.po
odoo_addons/currency_rate_date_check/i18n/pt_BR.po
odoo_addons/currency_rate_date_check/i18n/ro.po
odoo_addons/currency_rate_date_check/i18n/sk.po
odoo_addons/currency_rate_date_check/i18n/sl.po
odoo_addons/currency_rate_date_check/i18n/tr.po
odoo_addons/currency_rate_date_check/i18n/zh_CN.po
odoo_addons/currency_rate_date_check/images/date_check_company_config.jpg
odoo_addons/currency_rate_date_check/images/date_check_error_popup.jpg
odoo_addons/currency_rate_date_check/static/description/icon.png
odoo8_addon_currency_rate_date_check-8.0.1.0.0.99.dev19.dist-info/METADATA
odoo8_addon_currency_rate_date_check-8.0.1.0.0.99.dev19.dist-info/WHEEL
odoo8_addon_currency_rate_date_check-8.0.1.0.0.99.dev19.dist-info/namespace_packages.txt
odoo8_addon_currency_rate_date_check-8.0.1.0.0.99.dev19.dist-info/top_level.txt
odoo8_addon_currency_rate_date_check-8.0.1.0.0.99.dev19.dist-info/RECORD
